vortex_api/__init__.py
vortex_api/__version__.py
vortex_api/api.py
vortex_api/vortex_feed.py
vortex_api-2.0.2.dist-info/licenses/LICENSE
vortex_api-2.0.2.dist-info/METADATA
vortex_api-2.0.2.dist-info/WHEEL
vortex_api-2.0.2.dist-info/top_level.txt
vortex_api-2.0.2.dist-info/RECORD
