Metadata-Version: 2.4
Name: vortex_api
Version: 2.0.2
Summary: Vortex APIs to place orders in Rupeezy application
Home-page: https://vortex.rupeezy.in
Download-URL: https://github.com/RupeezyTech/pyvortex
Author: Astha Credit & Securities Pvt Ltd.
Author-email: tech@rupeezy.in
License: MIT
Classifier: Intended Audience :: Developers
Classifier: Intended Audience :: Financial and Insurance Industry
Classifier: Natural Language :: English
Classifier: License :: OSI Approved :: MIT License
Classifier: Programming Language :: Python :: 3
Classifier: Operating System :: OS Independent
Classifier: Topic :: Office/Business :: Financial :: Investment
Classifier: Topic :: Software Development :: Libraries :: Python Modules
Classifier: Topic :: Software Development :: Libraries
License-File: LICENSE
Requires-Dist: requests>=2.25.1
Requires-Dist: wrapt>=1.15.0
Requires-Dist: six>=1.11.0
Requires-Dist: pyOpenSSL>=17.5.0
Requires-Dist: python-dateutil>=2.6.1
Requires-Dist: autobahn[twisted]==19.11.2
Requires-Dist: service_identity>=18.1.0
Dynamic: author
Dynamic: author-email
Dynamic: classifier
Dynamic: description
Dynamic: description-content-type
Dynamic: download-url
Dynamic: home-page
Dynamic: license
Dynamic: license-file
Dynamic: requires-dist
Dynamic: summary
